renate/__init__.py
renate/defaults.py
renate/py.typed
renate/types.py
renate/benchmark/__init__.py
renate/benchmark/experiment_config.py
renate/benchmark/experimentation.py
renate/benchmark/scenarios.py
renate/benchmark/datasets/__init__.py
renate/benchmark/datasets/base.py
renate/benchmark/datasets/nlp_datasets.py
renate/benchmark/datasets/vision_datasets.py
renate/benchmark/datasets/wild_time_data.py
renate/benchmark/models/__init__.py
renate/benchmark/models/base.py
renate/benchmark/models/l2p.py
renate/benchmark/models/mlp.py
renate/benchmark/models/resnet.py
renate/benchmark/models/spromptmodel.py
renate/benchmark/models/transformer.py
renate/benchmark/models/vision_transformer.py
renate/cli/parsing_functions.py
renate/cli/run_experiment_with_scenario.py
renate/cli/run_remote_job.py
renate/cli/run_training.py
renate/data/__init__.py
renate/data/data_module.py
renate/data/datasets.py
renate/evaluation/__init__.py
renate/evaluation/evaluator.py
renate/evaluation/metrics/__init__.py
renate/evaluation/metrics/classification.py
renate/evaluation/metrics/performance_regression_metrics.py
renate/memory/__init__.py
renate/memory/buffer.py
renate/memory/storage.py
renate/models/__init__.py
renate/models/prediction_strategies.py
renate/models/renate_module.py
renate/models/task_identification_strategies.py
renate/models/layers/__init__.py
renate/models/layers/cn.py
renate/models/layers/shared_linear.py
renate/shift/__init__.py
renate/shift/detector.py
renate/shift/kernels.py
renate/shift/ks_detector.py
renate/shift/mmd_detectors.py
renate/shift/mmd_helpers.py
renate/training/__init__.py
renate/training/training.py
renate/updaters/__init__.py
renate/updaters/learner.py
renate/updaters/model_updater.py
renate/updaters/avalanche/__init__.py
renate/updaters/avalanche/learner.py
renate/updaters/avalanche/model_updater.py
renate/updaters/avalanche/plugins.py
renate/updaters/experimental/__init__.py
renate/updaters/experimental/er.py
renate/updaters/experimental/fine_tuning.py
Renate-0.5.2.dist-info/LICENSE
Renate-0.5.2.dist-info/METADATA
Renate-0.5.2.dist-info/NOTICE
Renate-0.5.2.dist-info/WHEEL
Renate-0.5.2.dist-info/top_level.txt
Renate-0.5.2.dist-info/RECORD
