Metadata-Version: 2.1
Name: Renate
Version: 0.5.2
Summary: Library for Continual Learning for Practitioners
Classifier: Development Status :: 3 - Alpha
Classifier: Intended Audience :: Developers
Classifier: Intended Audience :: Science/Research
Classifier: Topic :: Scientific/Engineering :: Artificial Intelligence
Classifier: License :: OSI Approved :: Apache Software License
Classifier: Programming Language :: Python :: 3
Requires-Python: <3.11,>=3.8
License-File: LICENSE
License-File: NOTICE
Requires-Dist: numpy <2.0.1,>=1.17.2
Requires-Dist: torch <1.13.2,>=1.10.0
Requires-Dist: pandas <2.2.3,>=1.4.0
Requires-Dist: boto3 <1.34.138,>=1.26.0
Requires-Dist: requests <2.32.4,>=2.32.0
Requires-Dist: sagemaker <2.224.3,>=2.218.0
Requires-Dist: syne-tune[aws,gpsearchers] <0.13.1,>=0.6.0
Requires-Dist: pytorch-lightning <1.9.6,>=1.8.0
Requires-Dist: Pillow <10.4.1,>=10.3.0
Requires-Dist: tabulate <0.9.1,>=0.9.0
Requires-Dist: tensorboardX <2.6.3,>=2.5.0
Requires-Dist: torchmetrics <0.11.5,>=0.11.0
Requires-Dist: torchvision <0.18.2,>=0.13.0
Requires-Dist: deepspeed <0.14.5,>=0.9.0
Requires-Dist: datasets <2.20.1,>=2.9.0
Requires-Dist: transformers <4.42.4,>=4.38.0
Requires-Dist: scipy <1.14.1,>=1.10.0
Provides-Extra: avalanche
Requires-Dist: avalanche-lib ==0.3.1 ; extra == 'avalanche'
Requires-Dist: torch <1.12.2,>=1.10.0 ; extra == 'avalanche'
Provides-Extra: benchmark
Requires-Dist: wild-time-data ==0.1.1 ; extra == 'benchmark'
Provides-Extra: dev
Requires-Dist: black ==24.4.2 ; extra == 'dev'
Requires-Dist: avalanche-lib ==0.3.1 ; extra == 'dev'
Requires-Dist: wild-time-data ==0.1.1 ; extra == 'dev'
Requires-Dist: torch <1.12.2,>=1.10.0 ; extra == 'dev'
Requires-Dist: pytest ==8.2.2 ; extra == 'dev'
Requires-Dist: pytest-cov ==5.0.0 ; extra == 'dev'
Requires-Dist: pytest-helpers-namespace ==2021.12.29 ; extra == 'dev'
